README.md
setup.py
nlp_preprocessor/__init__.py
nlp_preprocessor/preprocessing_rule.py
nlp_preprocessor/preprocessor.py
nlp_preprocessor.egg-info/PKG-INFO
nlp_preprocessor.egg-info/SOURCES.txt
nlp_preprocessor.egg-info/dependency_links.txt
nlp_preprocessor.egg-info/requires.txt
nlp_preprocessor.egg-info/top_level.txt