Metadata-Version: 2.1
Name: nlp-preprocessor
Version: 0.0.1
Summary: SpaCy component for modifying the string of a doc before tokenizing.
Home-page: UNKNOWN
Author: medSpaCy
Author-email: medspacy.dev@gmail.com
License: UNKNOWN
Platform: UNKNOWN
